idea_atlas/__init__.py
idea_atlas/agents.py
idea_atlas/research.py
idea_atlas/tasks.py
idea_atlas-0.2.3.dist-info/WHEEL
idea_atlas-0.2.3.dist-info/METADATA
idea_atlas-0.2.3.dist-info/RECORD
