Metadata-Version: 2.3
Name: idea-atlas
Version: 0.2.3
Summary: Atlas is a suite of standalone AI agents powered by crewai you can plug into your workflows.
Author: Alexandra Pop
Author-email: Alexandra Pop <alexandra.pop@digital.cabinet-office.gov.uk>
Requires-Dist: crewai[tools]>=0.186.1
Requires-Dist: pydantic>=2.10
Requires-Dist: python-dotenv>=1.1.1
Requires-Dist: selenium>=4.35.0
Requires-Dist: boto3>=1.40.35
Requires-Dist: ipykernel>=6.30.1
Requires-Python: >=3.11
Project-URL: Issues, https://github.com/co-cddo/gds-idea-atlas/issues
Project-URL: Repository, https://github.com/co-cddo/gds-idea-atlas.git
